ado_actuators/vllm_performance/__init__.py
ado_actuators/vllm_performance/actuator.py
ado_actuators/vllm_performance/actuator_definitions.yaml
ado_actuators/vllm_performance/actuator_parameters.py
ado_actuators/vllm_performance/deployment_management.py
ado_actuators/vllm_performance/env_manager.py
ado_actuators/vllm_performance/experiment_executor.py
ado_actuators/vllm_performance/datasets/india_url_in_b64_out.jsonl
ado_actuators/vllm_performance/datasets/valencia_url_in_b64_out.jsonl
ado_actuators/vllm_performance/experiments/performance_testing.yaml
ado_actuators/vllm_performance/experiments/performance_testing_geospatial.yaml
ado_actuators/vllm_performance/k8s/__init__.py
ado_actuators/vllm_performance/k8s/create_environment.py
ado_actuators/vllm_performance/k8s/manage_components.py
ado_actuators/vllm_performance/k8s/yaml_support/build_components.py
ado_actuators/vllm_performance/k8s/yaml_support/deployment.yaml
ado_actuators/vllm_performance/k8s/yaml_support/pvc.yaml
ado_actuators/vllm_performance/k8s/yaml_support/service.yaml
ado_actuators/vllm_performance/vllm_performance_test/__init__.py
ado_actuators/vllm_performance/vllm_performance_test/benchmark_models.py
ado_actuators/vllm_performance/vllm_performance_test/execute_benchmark.py
ado_actuators/vllm_performance/vllm_performance_test/execute_guidellm_benchmark.py
ado_actuators/vllm_performance/vllm_performance_test/get_benchmark_results.py
ado_actuators/vllm_performance/vllm_performance_test/guidellm_models.py
ado_actuators/vllm_performance/vllm_performance_test/payload_test.json
ado_actuators/vllm_performance/vllm_performance_test/payload_test_simple.json
ado_actuators/vllm_performance/vllm_performance_test/test.txt
ado_vllm_performance-1.4.1.dist-info/METADATA
ado_vllm_performance-1.4.1.dist-info/WHEEL
ado_vllm_performance-1.4.1.dist-info/top_level.txt
ado_vllm_performance-1.4.1.dist-info/RECORD
