Metadata-Version: 2.4
Name: ado-vllm-performance
Version: 1.4.1
Summary: VLLM performance testing actuator
Requires-Dist: kubernetes>=31.0.0
Requires-Dist: ado-core
Requires-Dist: vllm>=0.12.0
Requires-Dist: datasets>=2.20.0
Requires-Dist: guidellm>=0.5.3
